Workbook

Sheet Inputs
A1: TECHTONIC LLC — ASSUMPTIONS & INPUTS
A2: Yellow cells = EDITABLE INPUTS. Change these and all projections update automatically.
A4: REVENUE ASSUMPTIONS
A5: Initial Consultation Fee ($) | B5: 250
A6: Monthly Subscription Fee ($) | B6: 199
A7: Follow-Up Lab Fee ($) | B7: 150
A8: Consultation-to-Subscription Rate | B8: 0.8
A9: Monthly Patient Churn Rate | B9: 0.1
A11: COGS PER SUBSCRIBER / MONTH
A12: Pharmacy / Medication ($) | B12: 35
A13: Provider Fees ($) | B13: 15
A14: Lab Coordination ($) | B14: 5
A15: Platform Costs ($) | B15: 10
A16: Payment Processing (% of revenue) | B16: 0.03
A18: LOAN TERMS
A19: Loan Amount ($) | B19: 200000
A20: Loan Term (months) | B20: 120
A21: Annual Interest Rate | B21: 0.1125
A22: Monthly Payment (auto-calculated) | B22: =-PMT(B21/12,B20,B19)
A24: MONTHLY PATIENT TARGETS (Editable per month)
B25: Mo 1 | C25: Mo 2 | D25: Mo 3 | E25: Mo 4 | F25: Mo 5 | G25: Mo 6 | H25: Mo 7 | I25: Mo 8 | J25: Mo 9 | K25: Mo 10 | L25: Mo 11 | M25: Mo 12 | N25: TOTAL
A26: New Patients / Month | B26: 0 | C26: 4 | D26: 6 | E26: 10 | F26: 12 | G26: 14 | H26: 20 | I26: 22 | J26: 25 | K26: 28 | L26: 30 | M26: 35 | N26: =SUM(B26:M26)
A27: Follow-Up Lab Patients / Month | B27: 0 | C27: 0 | D27: 0 | E27: 0 | F27: 0 | G27: 3 | H27: 4 | I27: 5 | J27: 6 | K27: 7 | L27: 8 | M27: 9 | N27: =SUM(B27:M27)
A29: MONTHLY OPERATING EXPENSES (Editable per month)
B30: Mo 1 | C30: Mo 2 | D30: Mo 3 | E30: Mo 4 | F30: Mo 5 | G30: Mo 6 | H30: Mo 7 | I30: Mo 8 | J30: Mo 9 | K30: Mo 10 | L30: Mo 11 | M30: Mo 12 | N30: TOTAL
A31: Accounting | B31: 2000 | C31: 1000 | D31: 1000 | E31: 750 | F31: 750 | G31: 750 | H31: 750 | I31: 750 | J31: 750 | K31: 750 | L31: 750 | M31: 750 | N31: =SUM(B31:M31)
A32: Legal | B32: 5000 | C32: 2000 | D32: 1000 | E32: 500 | F32: 500 | G32: 500 | H32: 500 | I32: 500 | J32: 500 | K32: 500 | L32: 500 | M32: 500 | N32: =SUM(B32:M32)
A33: Consultants | B33: 10000 | C33: 5000 | D33: 3000 | E33: 2000 | F33: 1000 | G33: 0 | H33: 0 | I33: 0 | J33: 0 | K33: 0 | L33: 0 | M33: 0 | N33: =SUM(B33:M33)
A34: Technology / Platform | B34: 15000 | C34: 5000 | D34: 3000 | E34: 3000 | F34: 3000 | G34: 3000 | H34: 3000 | I34: 3000 | J34: 3000 | K34: 3000 | L34: 3000 | M34: 3000 | N34: =SUM(B34:M34)
A35: Digital Advertising | B35: 0 | C35: 8000 | D35: 10000 | E35: 12000 | F35: 12000 | G35: 12000 | H35: 15000 | I35: 15000 | J35: 15000 | K35: 15000 | L35: 15000 | M35: 15000 | N35: =SUM(B35:M35)
A36: Merchant Account Reserve | B36: 25000 | C36: 0 | D36: 0 | E36: 0 | F36: 0 | G36: 0 | H36: 0 | I36: 0 | J36: 0 | K36: 0 | L36: 0 | M36: 0 | N36: =SUM(B36:M36)
A37: Rent | B37: 1000 | C37: 1000 | D37: 1000 | E37: 1000 | F37: 1000 | G37: 1000 | H37: 1000 | I37: 1000 | J37: 1000 | K37: 1000 | L37: 1000 | M37: 1000 | N37: =SUM(B37:M37)
A38: Other / Insurance / Misc | B38: 3000 | C38: 1000 | D38: 1000 | E38: 1000 | F38: 1000 | G38: 1000 | H38: 1000 | I38: 1000 | J38: 1000 | K38: 1000 | L38: 1000 | M38: 1000 | N38: =SUM(B38:M38)
A39: Total Monthly OpEx | B39: =SUM(B31:B38) | C39: =SUM(C31:C38) | D39: =SUM(D31:D38) | E39: =SUM(E31:E38) | F39: =SUM(F31:F38) | G39: =SUM(G31:G38) | H39: =SUM(H31:H38) | I39: =SUM(I31:I38) | ... M39: =SUM(M31:M38) | N39: =SUM(B39:M39)

Sheet Subscribers
A1: SUBSCRIBER BUILD-UP (All Formulas — driven by Inputs sheet)
B3: Mo 1 | C3: Mo 2 | D3: Mo 3 | E3: Mo 4 | F3: Mo 5 | G3: Mo 6 | H3: Mo 7 | I3: Mo 8 | J3: Mo 9 | K3: Mo 10 | L3: Mo 11 | M3: Mo 12
A4: PATIENT ACQUISITION
A5: New Consultations | B5: =Inputs!B26 | C5: =Inputs!C26 | D5: =Inputs!D26 | E5: =Inputs!E26 | F5: =Inputs!F26 | G5: =Inputs!G26 | H5: =Inputs!H26 | I5: =Inputs!I26 | ... M5: =Inputs!M26
A6: Conversion Rate | B6: =Inputs!$B$8 | C6: =Inputs!$B$8 | D6: =Inputs!$B$8 | E6: =Inputs!$B$8 | F6: =Inputs!$B$8 | G6: =Inputs!$B$8 | H6: =Inputs!$B$8 | I6: =Inputs!$B$8 | ... M6: =Inputs!$B$8
A7: New Subscribers | B7: =ROUND(B5*B6,0) | C7: =ROUND(C5*C6,0) | D7: =ROUND(D5*D6,0) | E7: =ROUND(E5*E6,0) | F7: =ROUND(F5*F6,0) | G7: =ROUND(G5*G6,0) | H7: =ROUND(H5*H6,0) | I7: =ROUND(I5*I6,0) | ... M7: =ROUND(M5*M6,0)
A9: SUBSCRIBER DYNAMICS
A10: Beginning Active (Prior EOM) | B10: 0 | C10: =B13 | D10: =C13 | E10: =D13 | F10: =E13 | G10: =F13 | H10: =G13 | I10: =H13 | J10: =I13 | ... M10: =L13
A11: (+) New Subscribers | B11: =B7 | C11: =C7 | D11: =D7 | E11: =E7 | F11: =F7 | G11: =G7 | H11: =H7 | I11: =I7 | ... M11: =M7
A12: (-) Churned (churn rate x beginning) | B12: =ROUND(B10*Inputs!$B$9,0) | C12: =ROUND(C10*Inputs!$B$9,0) | D12: =ROUND(D10*Inputs!$B$9,0) | E12: =ROUND(E10*Inputs!$B$9,0) | F12: =ROUND(F10*Inputs!$B$9,0) | G12: =ROUND(G10*Inputs!$B$9,0) | H12: =ROUND(H10*Inputs!$B$9,0) | I12: =ROUND(I10*Inputs!$B$9,0) | ... M12: =ROUND(M10*Inputs!$B$9,0)
A13: End of Month Active | B13: =B10+B11-B12 | C13: =C10+C11-C12 | D13: =D10+D11-D12 | E13: =E10+E11-E12 | F13: =F10+F11-F12 | G13: =G10+G11-G12 | H13: =H10+H11-H12 | I13: =I10+I11-I12 | ... M13: =M10+M11-M12
A15: CUMULATIVE
A16: Cumulative New Patients | B16: =B5 | C16: =B16+C5 | D16: =C16+D5 | E16: =D16+E5 | F16: =E16+F5 | G16: =F16+G5 | H16: =G16+H5 | I16: =H16+I5 | J16: =I16+J5 | ... M16: =L16+M5
A17: Monthly Churn Rate (actual) | B17: =IF(B10=0,0,B12/B10) | C17: =IF(C10=0,0,C12/C10) | D17: =IF(D10=0,0,D12/D10) | E17: =IF(E10=0,0,E12/E10) | F17: =IF(F10=0,0,F12/F10) | G17: =IF(G10=0,0,G12/G10) | H17: =IF(H10=0,0,H12/H10) | I17: =IF(I10=0,0,I12/I10) | ... M17: =IF(M10=0,0,M12/M10)

Sheet PnL
A1: PROJECTED INCOME STATEMENT (P&L) — 12-MONTH PRO FORMA
B3: Mo 1 | C3: Mo 2 | D3: Mo 3 | E3: Mo 4 | F3: Mo 5 | G3: Mo 6 | H3: Mo 7 | I3: Mo 8 | J3: Mo 9 | K3: Mo 10 | L3: Mo 11 | M3: Mo 12 | N3: TOTAL
A4: REVENUE
A5: Consultation Revenue | B5: =Subscribers!B5*Inputs!$B$5 | C5: =Subscribers!C5*Inputs!$B$5 | D5: =Subscribers!D5*Inputs!$B$5 | E5: =Subscribers!E5*Inputs!$B$5 | F5: =Subscribers!F5*Inputs!$B$5 | G5: =Subscribers!G5*Inputs!$B$5 | H5: =Subscribers!H5*Inputs!$B$5 | I5: =Subscribers!I5*Inputs!$B$5 | ... M5: =Subscribers!M5*Inputs!$B$5 | N5: =SUM(B5:M5)
A6: Subscription Revenue | B6: =Subscribers!B13*Inputs!$B$6 | C6: =Subscribers!C13*Inputs!$B$6 | D6: =Subscribers!D13*Inputs!$B$6 | E6: =Subscribers!E13*Inputs!$B$6 | F6: =Subscribers!F13*Inputs!$B$6 | G6: =Subscribers!G13*Inputs!$B$6 | H6: =Subscribers!H13*Inputs!$B$6 | I6: =Subscribers!I13*Inputs!$B$6 | ... M6: =Subscribers!M13*Inputs!$B$6 | N6: =SUM(B6:M6)
A7: Follow-Up Lab Revenue | B7: =Inputs!B27*Inputs!$B$7 | C7: =Inputs!C27*Inputs!$B$7 | D7: =Inputs!D27*Inputs!$B$7 | E7: =Inputs!E27*Inputs!$B$7 | F7: =Inputs!F27*Inputs!$B$7 | G7: =Inputs!G27*Inputs!$B$7 | H7: =Inputs!H27*Inputs!$B$7 | I7: =Inputs!I27*Inputs!$B$7 | ... M7: =Inputs!M27*Inputs!$B$7 | N7: =SUM(B7:M7)
A8: Total Revenue | B8: =SUM(B5:B7) | C8: =SUM(C5:C7) | D8: =SUM(D5:D7) | E8: =SUM(E5:E7) | F8: =SUM(F5:F7) | G8: =SUM(G5:G7) | H8: =SUM(H5:H7) | I8: =SUM(I5:I7) | ... M8: =SUM(M5:M7) | N8: =SUM(B8:M8)
A10: COST OF GOODS SOLD
A11: Pharmacy / Medication | B11: =Subscribers!B13*Inputs!$B$12 | C11: =Subscribers!C13*Inputs!$B$12 | D11: =Subscribers!D13*Inputs!$B$12 | E11: =Subscribers!E13*Inputs!$B$12 | F11: =Subscribers!F13*Inputs!$B$12 | G11: =Subscribers!G13*Inputs!$B$12 | H11: =Subscribers!H13*Inputs!$B$12 | I11: =Subscribers!I13*Inputs!$B$12 | ... M11: =Subscribers!M13*Inputs!$B$12 | N11: =SUM(B11:M11)
A12: Provider Fees | B12: =Subscribers!B13*Inputs!$B$13 | C12: =Subscribers!C13*Inputs!$B$13 | D12: =Subscribers!D13*Inputs!$B$13 | E12: =Subscribers!E13*Inputs!$B$13 | F12: =Subscribers!F13*Inputs!$B$13 | G12: =Subscribers!G13*Inputs!$B$13 | H12: =Subscribers!H13*Inputs!$B$13 | I12: =Subscribers!I13*Inputs!$B$13 | ... M12: =Subscribers!M13*Inputs!$B$13 | N12: =SUM(B12:M12)
A13: Lab Coordination | B13: =Subscribers!B13*Inputs!$B$14 | C13: =Subscribers!C13*Inputs!$B$14 | D13: =Subscribers!D13*Inputs!$B$14 | E13: =Subscribers!E13*Inputs!$B$14 | F13: =Subscribers!F13*Inputs!$B$14 | G13: =Subscribers!G13*Inputs!$B$14 | H13: =Subscribers!H13*Inputs!$B$14 | I13: =Subscribers!I13*Inputs!$B$14 | ... M13: =Subscribers!M13*Inputs!$B$14 | N13: =SUM(B13:M13)
A14: Platform Costs | B14: =Subscribers!B13*Inputs!$B$15 | C14: =Subscribers!C13*Inputs!$B$15 | D14: =Subscribers!D13*Inputs!$B$15 | E14: =Subscribers!E13*Inputs!$B$15 | F14: =Subscribers!F13*Inputs!$B$15 | G14: =Subscribers!G13*Inputs!$B$15 | H14: =Subscribers!H13*Inputs!$B$15 | I14: =Subscribers!I13*Inputs!$B$15 | ... M14: =Subscribers!M13*Inputs!$B$15 | N14: =SUM(B14:M14)
A15: Payment Processing | B15: =B8*Inputs!$B$16 | C15: =C8*Inputs!$B$16 | D15: =D8*Inputs!$B$16 | E15: =E8*Inputs!$B$16 | F15: =F8*Inputs!$B$16 | G15: =G8*Inputs!$B$16 | H15: =H8*Inputs!$B$16 | I15: =I8*Inputs!$B$16 | ... M15: =M8*Inputs!$B$16 | N15: =SUM(B15:M15)
A16: Total COGS | B16: =SUM(B11:B15) | C16: =SUM(C11:C15) | D16: =SUM(D11:D15) | E16: =SUM(E11:E15) | F16: =SUM(F11:F15) | G16: =SUM(G11:G15) | H16: =SUM(H11:H15) | I16: =SUM(I11:I15) | ... M16: =SUM(M11:M15) | N16: =SUM(B16:M16)
A18: GROSS PROFIT
A19: Gross Profit | B19: =B8-B16 | C19: =C8-C16 | D19: =D8-D16 | E19: =E8-E16 | F19: =F8-F16 | G19: =G8-G16 | H19: =H8-H16 | I19: =I8-I16 | ... M19: =M8-M16 | N19: =SUM(B19:M19)
A20: Gross Margin % | B20: =IF(B8=0,"—",B19/B8) | C20: =IF(C8=0,"—",C19/C8) | D20: =IF(D8=0,"—",D19/D8) | E20: =IF(E8=0,"—",E19/E8) | F20: =IF(F8=0,"—",F19/F8) | G20: =IF(G8=0,"—",G19/G8) | H20: =IF(H8=0,"—",H19/H8) | I20: =IF(I8=0,"—",I19/I8) | ... N20: =IF(N8=0,"—",N19/N8)
A22: OPERATING EXPENSES (from Inputs sheet)
A23: Accounting | B23: =Inputs!B31 | C23: =Inputs!C31 | D23: =Inputs!D31 | E23: =Inputs!E31 | F23: =Inputs!F31 | G23: =Inputs!G31 | H23: =Inputs!H31 | I23: =Inputs!I31 | ... M23: =Inputs!M31 | N23: =SUM(B23:M23)
A24: Legal | B24: =Inputs!B32 | C24: =Inputs!C32 | D24: =Inputs!D32 | E24: =Inputs!E32 | F24: =Inputs!F32 | G24: =Inputs!G32 | H24: =Inputs!H32 | I24: =Inputs!I32 | ... M24: =Inputs!M32 | N24: =SUM(B24:M24)
A25: Consultants | B25: =Inputs!B33 | C25: =Inputs!C33 | D25: =Inputs!D33 | E25: =Inputs!E33 | F25: =Inputs!F33 | G25: =Inputs!G33 | H25: =Inputs!H33 | I25: =Inputs!I33 | ... M25: =Inputs!M33 | N25: =SUM(B25:M25)
A26: Technology / Platform | B26: =Inputs!B34 | C26: =Inputs!C34 | D26: =Inputs!D34 | E26: =Inputs!E34 | F26: =Inputs!F34 | G26: =Inputs!G34 | H26: =Inputs!H34 | I26: =Inputs!I34 | ... M26: =Inputs!M34 | N26: =SUM(B26:M26)
A27: Digital Advertising | B27: =Inputs!B35 | C27: =Inputs!C35 | D27: =Inputs!D35 | E27: =Inputs!E35 | F27: =Inputs!F35 | G27: =Inputs!G35 | H27: =Inputs!H35 | I27: =Inputs!I35 | ... M27: =Inputs!M35 | N27: =SUM(B27:M27)
A28: Merchant Account Reserve | B28: =Inputs!B36 | C28: =Inputs!C36 | D28: =Inputs!D36 | E28: =Inputs!E36 | F28: =Inputs!F36 | G28: =Inputs!G36 | H28: =Inputs!H36 | I28: =Inputs!I36 | ... M28: =Inputs!M36 | N28: =SUM(B28:M28)
A29: Rent | B29: =Inputs!B37 | C29: =Inputs!C37 | D29: =Inputs!D37 | E29: =Inputs!E37 | F29: =Inputs!F37 | G29: =Inputs!G37 | H29: =Inputs!H37 | I29: =Inputs!I37 | ... M29: =Inputs!M37 | N29: =SUM(B29:M29)
A30: Other / Insurance / Misc | B30: =Inputs!B38 | C30: =Inputs!C38 | D30: =Inputs!D38 | E30: =Inputs!E38 | F30: =Inputs!F38 | G30: =Inputs!G38 | H30: =Inputs!H38 | I30: =Inputs!I38 | ... M30: =Inputs!M38 | N30: =SUM(B30:M30)
A31: Total Operating Expenses | B31: =SUM(B23:B30) | C31: =SUM(C23:C30) | D31: =SUM(D23:D30) | E31: =SUM(E23:E30) | F31: =SUM(F23:F30) | G31: =SUM(G23:G30) | H31: =SUM(H23:H30) | I31: =SUM(I23:I30) | ... M31: =SUM(M23:M30) | N31: =SUM(B31:M31)
A33: OPERATING INCOME
A34: EBITDA | B34: =B19-B31 | C34: =C19-C31 | D34: =D19-D31 | E34: =E19-E31 | F34: =F19-F31 | G34: =G19-G31 | H34: =H19-H31 | I34: =I19-I31 | ... M34: =M19-M31 | N34: =SUM(B34:M34)
A36: DEBT SERVICE
A37: SBA Loan Payment | B37: =Inputs!$B$22 | C37: =Inputs!$B$22 | D37: =Inputs!$B$22 | E37: =Inputs!$B$22 | F37: =Inputs!$B$22 | G37: =Inputs!$B$22 | H37: =Inputs!$B$22 | I37: =Inputs!$B$22 | ... M37: =Inputs!$B$22 | N37: =SUM(B37:M37)
A39: NET INCOME
A40: Net Income | B40: =B34-B37 | C40: =C34-C37 | D40: =D34-D37 | E40: =E34-E37 | F40: =F34-F37 | G40: =G34-G37 | H40: =H34-H37 | I40: =I34-I37 | ... M40: =M34-M37 | N40: =SUM(B40:M40)

Sheet CashFlow
A1: PROJECTED CASH FLOW STATEMENT — 12 MONTHS
B3: Mo 1 | C3: Mo 2 | D3: Mo 3 | E3: Mo 4 | F3: Mo 5 | G3: Mo 6 | H3: Mo 7 | I3: Mo 8 | J3: Mo 9 | K3: Mo 10 | L3: Mo 11 | M3: Mo 12
A4: CASH INFLOWS
A5: Beginning Cash | B5: 0 | C5: =B17 | D5: =C17 | E5: =D17 | F5: =E17 | G5: =F17 | H5: =G17 | I5: =H17 | J5: =I17 | ... M5: =L17
A6: (+) Loan Proceeds | B6: =Inputs!$B$19 | C6: 0 | D6: 0 | E6: 0 | F6: 0 | G6: 0 | H6: 0 | I6: 0 | J6: 0 | K6: 0 | L6: 0 | M6: 0
A7: (+) Total Revenue | B7: =PnL!B8 | C7: =PnL!C8 | D7: =PnL!D8 | E7: =PnL!E8 | F7: =PnL!F8 | G7: =PnL!G8 | H7: =PnL!H8 | I7: =PnL!I8 | ... M7: =PnL!M8
A9: CASH OUTFLOWS
A10: (-) Total COGS | B10: =-PnL!B16 | C10: =-PnL!C16 | D10: =-PnL!D16 | E10: =-PnL!E16 | F10: =-PnL!F16 | G10: =-PnL!G16 | H10: =-PnL!H16 | I10: =-PnL!I16 | ... M10: =-PnL!M16
A11: (-) Operating Expenses | B11: =-PnL!B31 | C11: =-PnL!C31 | D11: =-PnL!D31 | E11: =-PnL!E31 | F11: =-PnL!F31 | G11: =-PnL!G31 | H11: =-PnL!H31 | I11: =-PnL!I31 | ... M11: =-PnL!M31
A12: (-) SBA Loan Payment | B12: =-PnL!B37 | C12: =-PnL!C37 | D12: =-PnL!D37 | E12: =-PnL!E37 | F12: =-PnL!F37 | G12: =-PnL!G37 | H12: =-PnL!H37 | I12: =-PnL!I37 | ... M12: =-PnL!M37
A13: Total Cash Outflows | B13: =SUM(B10:B12) | C13: =SUM(C10:C12) | D13: =SUM(D10:D12) | E13: =SUM(E10:E12) | F13: =SUM(F10:F12) | G13: =SUM(G10:G12) | H13: =SUM(H10:H12) | I13: =SUM(I10:I12) | ... M13: =SUM(M10:M12)
A15: NET CASH POSITION
A16: Net Cash Flow (Month) | B16: =B6+B7+B13 | C16: =C6+C7+C13 | D16: =D6+D7+D13 | E16: =E6+E7+E13 | F16: =F6+F7+F13 | G16: =G6+G7+G13 | H16: =H6+H7+H13 | I16: =I6+I7+I13 | ... M16: =M6+M7+M13
A17: Ending Cash Balance | B17: =B5+B16 | C17: =C5+C16 | D17: =D5+D16 | E17: =E5+E16 | F17: =F5+F16 | G17: =G5+G16 | H17: =H5+H16 | I17: =I5+I16 | ... M17: =M5+M16
A19: CASH POSITION ANALYSIS
A20: Minimum Cash Balance (12 mo) | B20: =MIN(B17:M17)
A21: Cash Positive All 12 Months? | B21: =IF(MIN(B17:M17)>=0,"YES","NO")
A22: Ending Cash (Month 12) | B22: =M17
A23: Month 12 DSCR | B23: =IF(PnL!M34>0,PnL!M34/PnL!M37,"Pre-break-even")

Sheet BalanceSheet
A1: PROJECTED BALANCE SHEET — END OF YEAR 1
B3: Amount
A4: ASSETS
A5: Cash | B5: =CashFlow!M17
A6: Accounts Receivable (1 mo subscription billing) | B6: =Subscribers!M13*Inputs!$B$6
A7: Merchant Account Reserve | B7: =SUM(Inputs!B36:M36)
A8: Technology / Platform (net of 20% depreciation) | B8: =PnL!N26*0.8
A9: Total Assets | B9: =SUM(B5:B8)
A11: LIABILITIES
A12: SBA Loan Balance (after 12 payments) | B12: =Amortization!E15
A13: Accounts Payable (1 mo COGS) | B13: =PnL!M16
A14: Total Liabilities | B14: =SUM(B12:B13)
A16: EQUITY
A17: Owner's Equity (enter your initial contribution) | B17: 0
A18: Retained Earnings (Year 1 Net Income) | B18: =PnL!N40
A19: Total Equity | B19: =SUM(B17:B18)
A21: Total Liabilities + Equity | B21: =B14+B19
A22: Balance Check (should equal Total Assets) | B22: =IF(ABS(B9-B21)<1,"BALANCED","CHECK ERROR")

Sheet KeyMetrics
A1: KEY METRICS DASHBOARD — ALL AUTO-CALCULATED
A3: Metric | B3: Value
A4: LOAN DETAILS
A5: Loan Amount | B5: =Inputs!B19
A6: Monthly Loan Payment | B6: =Inputs!B22
A7: Annual Debt Service | B7: =PnL!N37
A9: YEAR 1 FINANCIAL SUMMARY
A10: Total Year 1 Revenue | B10: =PnL!N8
A11: Total Year 1 COGS | B11: =PnL!N16
A12: Total Year 1 Gross Profit | B12: =PnL!N19
A13: Gross Margin | B13: =IF(PnL!N8=0,"—",PnL!N19/PnL!N8)
A14: Total Year 1 OpEx | B14: =PnL!N31
A15: Year 1 Net Income | B15: =PnL!N40
A17: CASH FLOW HEALTH
A18: Year 1 Ending Cash | B18: =CashFlow!M17
A19: Minimum Cash Balance | B19: =MIN(CashFlow!B17:M17)
A20: Cash Positive All 12 Months? | B20: =IF(MIN(CashFlow!B17:M17)>=0,"YES","NO")
A21: Month 12 Monthly Net Cash Flow | B21: =CashFlow!M16
A23: SUBSCRIBER METRICS
A24: Active Subscribers (Month 12) | B24: =Subscribers!M13
A25: Monthly Subscription Revenue (Month 12) | B25: =PnL!M6
A26: Annualized Revenue Run Rate (Month 12) | B26: =PnL!M8*12
A27: ARPU (Monthly) | B27: =Inputs!B6
A28: Churn Rate | B28: =Inputs!B9
A30: UNIT ECONOMICS
A31: COGS per Subscriber/Month | B31: =Inputs!B12+Inputs!B13+Inputs!B14+Inputs!B15
A32: Gross Profit per Subscriber/Month | B32: =Inputs!B6-(Inputs!B12+Inputs!B13+Inputs!B14+Inputs!B15)
A33: Subscriber Gross Margin | B33: =(Inputs!B6-(Inputs!B12+Inputs!B13+Inputs!B14+Inputs!B15))/Inputs!B6
A35: DEBT SERVICE COVERAGE
A36: Month 12 DSCR | B36: =IF(PnL!M34>0,PnL!M34/PnL!M37,"Pre-break-even")
A37: Required Minimum DSCR | B37: 1.15x — 1.25x

Sheet Amortization
A1: SBA LOAN AMORTIZATION — 24 MONTHS (All Formulas)
A3: Month | B3: Payment | C3: Principal | D3: Interest | E3: Balance
A4: 1 | B4: =Inputs!$B$22 | C4: =B4-D4 | D4: =ROUND(Inputs!$B$19*Inputs!$B$21/12,2) | E4: =Inputs!$B$19-C4
A5: 2 | B5: =Inputs!$B$22 | C5: =B5-D5 | D5: =ROUND(E4*Inputs!$B$21/12,2) | E5: =E4-C5
A6: 3 | B6: =Inputs!$B$22 | C6: =B6-D6 | D6: =ROUND(E5*Inputs!$B$21/12,2) | E6: =E5-C6
A7: 4 | B7: =Inputs!$B$22 | C7: =B7-D7 | D7: =ROUND(E6*Inputs!$B$21/12,2) | E7: =E6-C7
A8: 5 | B8: =Inputs!$B$22 | C8: =B8-D8 | D8: =ROUND(E7*Inputs!$B$21/12,2) | E8: =E7-C8
A9: 6 | B9: =Inputs!$B$22 | C9: =B9-D9 | D9: =ROUND(E8*Inputs!$B$21/12,2) | E9: =E8-C9
A10: 7 | B10: =Inputs!$B$22 | C10: =B10-D10 | D10: =ROUND(E9*Inputs!$B$21/12,2) | E10: =E9-C10
A11: 8 | B11: =Inputs!$B$22 | C11: =B11-D11 | D11: =ROUND(E10*Inputs!$B$21/12,2) | E11: =E10-C11
A12: 9 | B12: =Inputs!$B$22 | C12: =B12-D12 | D12: =ROUND(E11*Inputs!$B$21/12,2) | E12: =E11-C12
A13: 10 | B13: =Inputs!$B$22 | C13: =B13-D13 | D13: =ROUND(E12*Inputs!$B$21/12,2) | E13: =E12-C13
A14: 11 | B14: =Inputs!$B$22 | C14: =B14-D14 | D14: =ROUND(E13*Inputs!$B$21/12,2) | E14: =E13-C14
A15: 12 | B15: =Inputs!$B$22 | C15: =B15-D15 | D15: =ROUND(E14*Inputs!$B$21/12,2) | E15: =E14-C15
A16: 13 | B16: =Inputs!$B$22 | C16: =B16-D16 | D16: =ROUND(E15*Inputs!$B$21/12,2) | E16: =E15-C16
... A27: 24 | B27: =Inputs!$B$22 | C27: =B27-D27 | D27: =ROUND(E26*Inputs!$B$21/12,2) | E27: =E26-C27
A29: Year 1 | B29: =SUM(B4:B15) | C29: =SUM(C4:C15) | D29: =SUM(D4:D15)
A30: Year 2 | B30: =SUM(B16:B27) | C30: =SUM(C16:C27) | D30: =SUM(D16:D27)

Sheet UseOfFunds
A1: USE OF FUNDS — SBA EXPRESS LOAN
A2: Edit the amounts below. % of Total updates automatically.
A3: Category | B3: Amount | C3: % of Total
A4: Technology & Platform Infrastructure | B4: 50000 | C4: =B4/B$10
A5: Digital Advertising & Customer Acquisition | B5: 48000 | C5: =B5/B$10
A6: Professional Services (Legal, Accounting, Consulting) | B6: 43000 | C6: =B6/B$10
A7: Merchant Account Reserve | B7: 25000 | C7: =B7/B$10
A8: Working Capital & Operating Reserve | B8: 22000 | C8: =B8/B$10
A9: Rent & Facilities | B9: 12000 | C9: =B9/B$10
A10: TOTAL | B10: =SUM(B4:B9) | C10: =B10/B10
A12: Loan Amount (from Inputs) | B12: =Inputs!B19
A13: Difference (should be $0) | B13: =B10-B12
